token_scan/__init__.py
token_scan-0.1.0.dist-info/METADATA
token_scan-0.1.0.dist-info/WHEEL
token_scan-0.1.0.dist-info/RECORD
