Metadata-Version: 2.1
Name: token-scan
Version: 0.1.0
Summary: 
Author: Ethan-ahnlabio
Author-email: ethan@ahnlab.io
Requires-Python: >=3.11,<4.0
Classifier: Programming Language :: Python :: 3
Classifier: Programming Language :: Python :: 3.11
Requires-Dist: bicscan-engine (>=0.1.0,<0.2.0)
